README.md
requirements.txt
setup.py
word_knn/__init__.py
word_knn/__main__.py
word_knn/closest_words.py
word_knn/nlpl_retriever.py
word_knn/version.py
word_knn.egg-info/PKG-INFO
word_knn.egg-info/SOURCES.txt
word_knn.egg-info/dependency_links.txt
word_knn.egg-info/entry_points.txt
word_knn.egg-info/requires.txt
word_knn.egg-info/top_level.txt